tests/__init__.py
tests/test_main.py
thousandeyessdk/__init__.py
thousandeyessdk/agent.py
thousandeyessdk/agents.py
thousandeyessdk/alert.py
thousandeyessdk/alert_notifications.py
thousandeyessdk/alert_rule.py
thousandeyessdk/alert_rules.py
thousandeyessdk/alerts.py
thousandeyessdk/endpoint_test.py
thousandeyessdk/endpoint_tests.py
thousandeyessdk/enum.py
thousandeyessdk/list_like.py
thousandeyessdk/test.py
thousandeyessdk/tests.py
thousandeyessdk-0.0.3.dist-info/LICENSE
thousandeyessdk-0.0.3.dist-info/METADATA
thousandeyessdk-0.0.3.dist-info/WHEEL
thousandeyessdk-0.0.3.dist-info/top_level.txt
thousandeyessdk-0.0.3.dist-info/RECORD
